jobscraper/__init__.py
jobscraper/scraper.py
jobscraper-0.2.dist-info/DESCRIPTION.rst
jobscraper-0.2.dist-info/METADATA
jobscraper-0.2.dist-info/RECORD
jobscraper-0.2.dist-info/WHEEL
jobscraper-0.2.dist-info/metadata.json
jobscraper-0.2.dist-info/top_level.txt
